geomancy/__description__.txt
geomancy/__init__.py
geomancy/checks/__init__.py
geomancy/checks/base.py
geomancy/checks/env.py
geomancy/checks/exec.py
geomancy/checks/path.py
geomancy/checks/platform.py
geomancy/checks/python.py
geomancy/checks/test.py
geomancy/checks/utils.py
geomancy/checks/version.py
geomancy/checks/aws/__init__.py
geomancy/checks/aws/base.py
geomancy/checks/aws/iam.py
geomancy/checks/aws/s3.py
geomancy/checks/aws/ssm.py
geomancy/entrypoints/__init__.py
geomancy/entrypoints/check.py
geomancy/entrypoints/config.py
geomancy/entrypoints/environment.py
geomancy/entrypoints/geo.py
geomancy/entrypoints/run.py
geomancy/entrypoints/utils.py
geomancy/environment/__init__.py
geomancy/environment/dotenv.py
geomancy-1.2.4.dist-info/LICENSE
geomancy-1.2.4.dist-info/METADATA
geomancy-1.2.4.dist-info/WHEEL
geomancy-1.2.4.dist-info/entry_points.txt
geomancy-1.2.4.dist-info/top_level.txt
geomancy-1.2.4.dist-info/RECORD
