Metadata-Version: 2.1
Name: geomancy
Version: 1.2.4
Summary: Geomancy validates deployment and development environments
Author: Justin Lorieau
Keywords: .env,dotenv,env,env var,environment,environment variable,deployment,validation
Classifier: Programming Language :: Python :: 3 :: Only
Classifier: Programming Language :: Python :: 3
Classifier: Programming Language :: Python :: 3.11
Classifier: Environment :: Console
Classifier: Environment :: Web Environment
Classifier: Intended Audience :: Developers
Classifier: Intended Audience :: Information Technology
Classifier: License :: OSI Approved :: MIT License
Classifier: Topic :: Software Development :: Bug Tracking
Classifier: Topic :: Software Development :: Debuggers
Classifier: Topic :: Software Development :: Quality Assurance
Classifier: Topic :: Software Development :: Testing
Classifier: Topic :: Software Development :: Testing :: Acceptance
Classifier: Topic :: System :: Monitoring
Classifier: Topic :: System :: Systems Administration
Classifier: Topic :: Utilities
Classifier: Development Status :: 4 - Beta
Requires-Python: >=3.11
License-File: LICENSE
Requires-Dist: thatway >=0.5
Requires-Dist: pyyaml >=6.0
Requires-Dist: click >=8.1
Requires-Dist: click-default-group
Requires-Dist: rich >=13
Provides-Extra: all
Requires-Dist: boto3 >=1.28 ; extra == 'all'
Provides-Extra: aws
Requires-Dist: boto3 >=1.28 ; extra == 'aws'
Provides-Extra: dev
Requires-Dist: pytest >=7.4 ; extra == 'dev'
Requires-Dist: twine >=4.0 ; extra == 'dev'
Requires-Dist: build ; extra == 'dev'
Requires-Dist: black[d] ; extra == 'dev'
Requires-Dist: vcrpy <5.0 ; extra == 'dev'
Requires-Dist: pytest-recording ; extra == 'dev'
Provides-Extra: docs
Requires-Dist: sphinx ; extra == 'docs'
Requires-Dist: furo >=2023 ; extra == 'docs'
Requires-Dist: sphinx-design >=0.4 ; extra == 'docs'
Requires-Dist: myst-parser >=2.0 ; extra == 'docs'
Requires-Dist: sphinx-remove-toctrees ; extra == 'docs'
Requires-Dist: towncrier ; extra == 'docs'
